tensorflow_datasets/__init__.py
tensorflow_datasets/import_test.py
tf_datasets-0.0.1.dist-info/METADATA
tf_datasets-0.0.1.dist-info/RECORD
tf_datasets-0.0.1.dist-info/WHEEL
tf_datasets-0.0.1.dist-info/top_level.txt
