Metadata-Version: 2.1
Name: tf-datasets
Version: 0.0.1
Summary: tensorflow/datasets
Home-page: http://github.com/tensorflow/datasets
Author: Google Inc.
Author-email: no-reply@google.com
License: Apache 2.0
Keywords: tensorflow machine learning datasets
Platform: UNKNOWN
Classifier: Development Status :: 4 - Beta
Classifier: Intended Audience :: Developers
Classifier: Intended Audience :: Science/Research
Classifier: License :: OSI Approved :: Apache Software License
Classifier: Topic :: Scientific/Engineering :: Artificial Intelligence
Provides-Extra: tensorflow
Provides-Extra: tests
Provides-Extra: tensorflow_gpu
Requires-Dist: future
Requires-Dist: six
Provides-Extra: tensorflow
Requires-Dist: tensorflow (>=1.9.0); extra == 'tensorflow'
Provides-Extra: tensorflow_gpu
Requires-Dist: tensorflow-gpu (>=1.9.0); extra == 'tensorflow_gpu'
Provides-Extra: tests
Requires-Dist: pytest; extra == 'tests'
